votedperceptron/__init__.py
votedperceptron/multiclassclassifier.py
votedperceptron/votedperceptron.py
votedperceptron-1.0.0.dist-info/DESCRIPTION.rst
votedperceptron-1.0.0.dist-info/METADATA
votedperceptron-1.0.0.dist-info/RECORD
votedperceptron-1.0.0.dist-info/WHEEL
votedperceptron-1.0.0.dist-info/metadata.json
votedperceptron-1.0.0.dist-info/top_level.txt
