Metadata-Version: 2.0
Name: votedperceptron
Version: 1.0.0
Summary: An implementation of the voted-perceptron algorithm. 
Home-page: https://github.com/bmgee/votedperceptron
Author: B. Gee
Author-email: bgee@codeapex.com
License: Apache License 2.0
Keywords: voted perceptron machine learning neural network python
Platform: UNKNOWN
Classifier: Development Status :: 5 - Production/Stable
Classifier: Intended Audience :: Developers
Classifier: Intended Audience :: Science/Research
Classifier: Topic :: Scientific/Engineering :: Artificial Intelligence
Classifier: License :: OSI Approved :: Apache Software License
Classifier: Programming Language :: Python :: 3 :: Only
Requires-Dist: multiprocess
Requires-Dist: numpy
